SolarY/__init__.py
SolarY/_version.py
SolarY/_config/__init__.py
SolarY/_config/constants.ini
SolarY/_config/paths.ini
SolarY/_config/SPICE/__init__.py
SolarY/asteroid/__init__.py
SolarY/asteroid/physp.py
SolarY/auxiliary/__init__.py
SolarY/auxiliary/config.py
SolarY/auxiliary/download.py
SolarY/auxiliary/parse.py
SolarY/auxiliary/reader.py
SolarY/general/__init__.py
SolarY/general/astrodyn.py
SolarY/general/geometry.py
SolarY/general/photometry.py
SolarY/general/vec.py
SolarY/instruments/__init__.py
SolarY/instruments/camera.py
SolarY/instruments/optics.py
SolarY/instruments/telescope.py
SolarY/neo/__init__.py
SolarY/neo/data.py
tests/test_asteroid/__init__.py
tests/test_asteroid/test_physp.py
tests/test_auxiliary/__init__.py
tests/test_auxiliary/test_config.py
tests/test_auxiliary/test_download.py
tests/test_auxiliary/test_parse.py
tests/test_auxiliary/test_reader.py
tests/test_general/__init__.py
tests/test_general/test_astrodyn.py
tests/test_general/test_geometry.py
tests/test_general/test_photometry.py
tests/test_general/test_vec.py
tests/test_instruments/__init__.py
tests/test_instruments/test_camera.py
tests/test_instruments/test_optics.py
tests/test_instruments/test_telescope.py
tests/test_neo/__init__.py
tests/test_neo/test_data.py
SolarY-0.6.1.dist-info/LICENSE
SolarY-0.6.1.dist-info/METADATA
SolarY-0.6.1.dist-info/WHEEL
SolarY-0.6.1.dist-info/top_level.txt
SolarY-0.6.1.dist-info/zip-safe
SolarY-0.6.1.dist-info/RECORD
