Metadata-Version: 2.1
Name: SolarY
Version: 0.6.1
Summary: A Space Science library for asteroid, comets and meteors.
Home-page: https://github.com/ThomasAlbin/SolarY
Author: attr: SolarY.__author__
License: MIT License
Project-URL: Source, https://github.com/ThomasAlbin/SolarY
Project-URL: Tracker, https://github.com/ThomasAlbin/SolarY/issues
Keywords: asteroid,comets,meteors
Platform: unix
Platform: linux
Platform: osx
Platform: win32
Classifier: Development Status :: 4 - Beta
Classifier: Intended Audience :: Developers
Classifier: Intended Audience :: End Users/Desktop
Classifier: Topic :: Software Development :: Build Tools
Classifier: License :: OSI Approved :: MIT License
Classifier: Programming Language :: Python :: 3
Classifier: Programming Language :: Python :: 3.7
Classifier: Programming Language :: Python :: 3.8
Classifier: Programming Language :: Python :: 3.9
Requires-Python: >=3.7
Requires-Dist: certifi
Requires-Dist: requests
Requires-Dist: spiceypy
